decoder8X3(Behavioural Modelling).v
module dco(IN, OUT);
	input [2:0]IN;
	output [7:0]OUT;
	reg [7:0]OUT;
	always @(*) begin
		case(IN)
			3'b000: OUT = 8'b00000001;
			3'b001: OUT = 8'b00000010;
			3'b010: OUT = 8'b00000100;
			3'b011: OUT = 8'b00001000;
			3'b100: OUT = 8'b00010000;
			3'b101: OUT = 8'b00100000;
			3'b110: OUT = 8'b01000000;
			3'b111: OUT = 8'b10000000;
		endcase
	end
endmodule

module test;
	reg [2:0]in;
	wire [7:0]out;
	dco gco(in, out);
	initial begin
		$dumpfile("decoder8X3(Behavioural Modelling).vcd");
		$dumpvars(0,test);
		$display("Input\tOutput");
		$monitor("%b\t%b",in,out);
		#0  in = 3'b000;
		#10 in = 3'b001;
		#10 in = 3'b010;
		#10 in = 3'b011;
		#10 in = 3'b100;
		#10 in = 3'b101;
		#10 in = 3'b110;
		#10 in = 3'b111;
		#10
		$finish;
	end
endmodule

decoder8X3(Behavioural Modelling).vcd
$date
	Thu Feb  6 16:42:32 2020
$end
$version
	Icarus Verilog
$end
$timescale
	1s
$end
$scope module test $end
$var wire 8 ! out [7:0] $end
$var reg 3 " in [2:0] $end
$scope module gco $end
$var wire 3 # IN [2:0] $end
$var reg 8 $ OUT [7:0] $end
$upscope $end
$upscope $end
$enddefinitions $end
#0
$dumpvars
b1 $
b0 #
b0 "
b1 !
$end
#10
b10 !
b10 $
b1 "
b1 #
#20
b100 !
b100 $
b10 "
b10 #
#30
b1000 !
b1000 $
b11 "
b11 #
#40
b10000 !
b10000 $
b100 "
b100 #
#50
b100000 !
b100000 $
b101 "
b101 #
#60
b1000000 !
b1000000 $
b110 "
b110 #
#70
b10000000 !
b10000000 $
b111 "
b111 #
