fullAdder.v
module fa(A,B,Cin,Cout,Sum);
input A,B,Cin;
output Cout,Sum;
assign Cout = (A&B)|(Cin&(A^B));
assign Sum = A^B^Cin;
endmodule

module test;
reg a,b,cin;
wire cout,sum;
fa ga(a,b,cin,cout,sum);
initial begin
$dumpfile("fullAdder.vcd");
$dumpvars(0,test);
$display("A\tB\tCin\tCout\tSum");
$monitor("%b\t%b\t%b\t%b\t%b",a,b,cin,cout,sum);
#0 a=0;b=0;cin=0;
#10 a=0;b=0;cin=1;
#10 a=0;b=1;cin=0;
#10 a=0;b=1;cin=1;
#10 a=1;b=0;cin=0;
#10 a=1;b=0;cin=1;
#10 a=1;b=1;cin=0;
#10 a=1;b=1;cin=1;
#10
$finish;
end
endmodule

fullAdder.vcd
$date
	Thu Jan 23 16:32:47 2020
$end
$version
	Icarus Verilog
$end
$timescale
	1s
$end
$scope module test $end
$var wire 1 ! sum $end
$var wire 1 " cout $end
$var reg 1 # a $end
$var reg 1 $ b $end
$var reg 1 % cin $end
$scope module ga $end
$var wire 1 # A $end
$var wire 1 $ B $end
$var wire 1 % Cin $end
$var wire 1 " Cout $end
$var wire 1 ! Sum $end
$upscope $end
$upscope $end
$enddefinitions $end
#0
$dumpvars
0%
0$
0#
0"
0!
$end
#10
1!
1%
#20
0%
1$
#30
1"
0!
1%
#40
0"
1!
0%
0$
1#
#50
1"
0!
1%
#60
0%
1$
#70
1!
1%
