mux2X1(Data Flow Modelling).v
module m1(A, B, C, Select);
	input A, B, Select;
	output C;
	assign C = Select ? B : A;
endmodule

module test;
	reg a, b, select;
	wire c;
	m1 g1(a, b, c, select);
	initial begin
		$dumpfile("mux2X1(Data Flow Modelling).vcd");
		$dumpvars(0,test);
		$display("A\tB\tSelect\tC");
		$monitor("%b\t%b\t%b\t%b",a,b,select,c);
		#0  a=0;b=0;select=0;
		#10 a=0;b=0;select=1;
		#10 a=0;b=1;select=0;
		#10 a=0;b=1;select=1;
		#10 a=1;b=0;select=0;
		#10 a=1;b=0;select=1;
		#10 a=1;b=1;select=0;
		#10 a=1;b=1;select=1;
		#10 
		$finish;
	end
endmodule

mux2X1(Data Flow Modelling).vcd
$date
	Fri Feb 14 14:22:53 2020
$end
$version
	Icarus Verilog
$end
$timescale
	1s
$end
$scope module test $end
$var wire 1 ! c $end
$var reg 1 " a $end
$var reg 1 # b $end
$var reg 1 $ select $end
$scope module g1 $end
$var wire 1 " A $end
$var wire 1 # B $end
$var wire 1 $ Select $end
$var wire 1 ! C $end
$upscope $end
$upscope $end
$enddefinitions $end
#0
$dumpvars
0$
0#
0"
0!
$end
#10
1$
#20
0$
1#
#30
1!
1$
#40
0$
0#
1"
#50
0!
1$
#60
1!
0$
1#
#70
1$
